easyfatt_db_connector/__init__.py
easyfatt_db_connector/constants.py
easyfatt_db_connector/core/__init__.py
easyfatt_db_connector/core/connection/__init__.py
easyfatt_db_connector/core/connection/_base.py
easyfatt_db_connector/core/connection/_fdb.py
easyfatt_db_connector/core/connection/_sqlalchemy.py
easyfatt_db_connector/core/exceptions.py
easyfatt_db_connector/orm/__init__.py
easyfatt_db_connector/orm/dynamic/__init__.py
easyfatt_db_connector/orm/dynamic/factory.py
easyfatt_db_connector/orm/static/__init__.py
easyfatt_db_connector/orm/static/models.py
easyfatt_db_connector/utils/__init__.py
easyfatt_db_connector/utils/decorators.py
easyfatt_db_connector/utils/downloader.py
easyfatt_db_connector/xml/__init__.py
easyfatt_db_connector/xml/common/__init__.py
easyfatt_db_connector/xml/common/fields.py
easyfatt_db_connector/xml/common/mapper.py
easyfatt_db_connector/xml/common/README.md
easyfatt_db_connector/xml/company.py
easyfatt_db_connector/xml/document.py
easyfatt_db_connector/xml/product.py
easyfatt_db_connector/xml/README.md
easyfatt_db_connector/xml/root.py
easyfatt_db_connector/xml/vat_code.py
easyfatt_db_connector-0.3.2.dist-info/LICENSE
easyfatt_db_connector-0.3.2.dist-info/METADATA
easyfatt_db_connector-0.3.2.dist-info/WHEEL
easyfatt_db_connector-0.3.2.dist-info/RECORD
