Metadata-Version: 2.1
Name: easyfatt-db-connector
Version: 0.3.2
Summary: 
Home-page: https://github.com/LukeSavefrogs/easyfatt-db-connector/
License: MIT
Author: Luca Salvarani
Author-email: lucasalvarani99@gmail.com
Requires-Python: >=3.8,<3.12
Classifier: License :: OSI Approved :: MIT License
Classifier: Programming Language :: Python :: 3
Classifier: Programming Language :: Python :: 3.8
Classifier: Programming Language :: Python :: 3.9
Classifier: Programming Language :: Python :: 3.10
Classifier: Programming Language :: Python :: 3.11
Requires-Dist: fdb (>=2.0.2,<3.0.0)
Requires-Dist: lxml (>=4.9.3,<5.0.0)
Requires-Dist: lxml-stubs (>=0.4.0,<0.5.0)
Requires-Dist: requests (>=2.30.0,<3.0.0)
Requires-Dist: sqlalchemy (>=2.0.12,<3.0.0)
Requires-Dist: sqlalchemy-firebird (>=2.0.0,<3.0.0)
Project-URL: Repository, https://github.com/LukeSavefrogs/easyfatt-db-connector/
